{
    "goods-outbound-controller": {
        "name": "goods-outbound-controller",
        "region": "europe-west1",
        "env": "stable",
        "service": "goods-outbound-controller",
        "memory_size": 1,
        "type": "memcached",
        "cpu_count": 1,
        "node_count": 1,
        "cache_cname": "goods-outbound-controller-memcache-memorystore.europe-west1.caches.stable.gcp.groupondev.com.",
        "cnames": "goods-outbound-controller-memcache.europe-west1.caches.stable.gcp.groupondev.com.",
        "jira_ticket": "raas-1924"
    },
    "content-pages": {
        "name": "content-pages",
        "region": "europe-west1",
        "env": "stable",
        "service": "content-pages",
        "memory_size": 1,
        "type": "memcached",
        "cpu_count": 1,
        "node_count": 1,
        "cache_cname": "content-pages-memcache-memorystore.europe-west1.caches.stable.gcp.groupondev.com.",
        "cnames": "content-pages-memcache.europe-west1.caches.stable.gcp.groupondev.com.",
        "jira_ticket": "raas-2446"
    },
    "checkout-itier": {
        "name": "checkout-itier",
        "region": "europe-west1",
        "env": "stable",
        "service": "checkout-itier",
        "memory_size": 1,
        "type": "memcached",
        "cpu_count": 1,
        "node_count": 1,
        "cache_cname": "checkout-itier-memcache-memorystore.europe-west1.caches.stable.gcp.groupondev.com.",
        "cnames": "checkout-memcache.europe-west1.caches.stable.gcp.groupondev.com.",
        "jira_ticket": "raas-2322"
    },
    "usr-sessions": {
        "name": "usr-sessions",
        "region": "europe-west1",
        "env": "stable",
        "service": "user_sessions",
        "memory_size": 1,
        "type": "memcached",
        "cpu_count": 1,
        "node_count": 1,
        "cache_cname": "usr-sessions-memcache-memorystore.europe-west1.caches.stable.gcp.groupondev.com.",
        "cnames": "usr-sessions-memcache.europe-west1.caches.stable.gcp.groupondev.com.",
        "jira_ticket": "raas-2598"
    },
    "layout-service": {
        "name": "layout-service",
        "region": "europe-west1",
        "env": "stable",
        "service": "layout-service",
        "memory_size": 1,
        "type": "memcached",
        "cpu_count": 1,
        "node_count": 1,
        "cache_cname": "layout-service-memcache-memorystore.europe-west1.caches.stable.gcp.groupondev.com.",
        "cnames": "layout-service-memcache.europe-west1.caches.stable.gcp.groupondev.com.",
        "jira_ticket": "raas-2422"
    },
    "pull": {
        "name": "pull",
        "region": "europe-west1",
        "env": "stable",
        "service": "pull",
        "memory_size": 1,
        "type": "memcached",
        "cpu_count": 1,
        "node_count": 1,
        "cache_cname": "pull-memcache-memorystore.europe-west1.caches.stable.gcp.groupondev.com.",
        "cnames": "pull-memcache.europe-west1.caches.stable.gcp.groupondev.com.",
        "jira_ticket": "raas-2474"
    },
    "sub-center": {
        "name": "sub-center",
        "region": "europe-west1",
        "env": "stable",
        "service": "sub_center",
        "memory_size": 1,
        "type": "memcached",
        "cpu_count": 1,
        "node_count": 1,
        "cache_cname": "sub-center-memcache-memorystore.europe-west1.caches.stable.gcp.groupondev.com.",
        "cnames": "sub-center-memcache.europe-west1.caches.stable.gcp.groupondev.com.",
        "jira_ticket": "raas-1488"
    },
    "subscription-flow": {
        "name": "subscription-flow",
        "region": "europe-west1",
        "env": "stable",
        "service": "subscription-flow",
        "memory_size": 1,
        "type": "memcached",
        "cpu_count": 1,
        "node_count": 1,
        "cache_cname": "subscription-flow-memcache-memorystore.europe-west1.caches.stable.gcp.groupondev.com.",
        "cnames": "subscription-flow-memcache.europe-west1.caches.stable.gcp.groupondev.com.",
        "jira_ticket": "raas-1492"
    },
    "getaways-browse": {
        "name": "getaways-browse",
        "region": "europe-west1",
        "env": "stable",
        "service": "getaways-browse",
        "memory_size": 1,
        "type": "memcached",
        "cpu_count": 1,
        "node_count": 1,
        "cache_cname": "getaways-browse-memcache-memorystore.europe-west1.caches.stable.gcp.groupondev.com.",
        "cnames": "getaways-browse-memcache.europe-west1.caches.stable.gcp.groupondev.com.",
        "jira_ticket": "raas-1852"
    },
    "occasions": {
        "name": "occasions",
        "region": "europe-west1",
        "env": "stable",
        "service": "occasions",
        "memory_size": 1,
        "type": "memcached",
        "cpu_count": 1,
        "node_count": 1,
        "cache_cname": "occasions-memcache-memorystore.europe-west1.caches.stable.gcp.groupondev.com.",
        "cnames": "occasions-memcache.europe-west1.caches.stable.gcp.groupondev.com.",
        "jira_ticket": "raas-1824"
    }
}